{
  "timestamp": "2025-06-05T00:18:57.032767+00:00",
  "current_phase": "email_system_complete",
  "phase_number": 1,
  "step": "automatic_sending_confirmed",
  "progress_percentage": 100,
  "estimated_completion": "5_minutes",
  "description": "main.py修正完了、cron自動送信復旧確認、今夜から正常送信開始",
  "next_immediate_action": "メール受信監視・システム運用継続",
  "git_status": "274 files changed (massive) - 主要: AI_AUTOMATIC_INSTRUCTIONS.md, AI_GITHUB_AUTO_REPORT.md, GOLDEN_VERSION.py",
  "active_files": [
    "AI_AUTOMATIC_INSTRUCTIONS.md",
    "AI_GITHUB_AUTO_REPORT.md",
    "GOLDEN_VERSION.py",
    "HANDOVER_PROMPT.md",
    "PROJECT_STATUS.md"
  ],
  "project_name": "email",
  "auto_detected": true
}